rosbag_tools/__init__.py
rosbag_tools/__main__.py
rosbag_tools/base.py
rosbag_tools/exceptions.py
rosbag_tools/utils.py
rosbag_tools/clip/README.md
rosbag_tools/clip/__init__.py
rosbag_tools/clip/__main__.py
rosbag_tools/clip/clipper.py
rosbag_tools/clip/main.py
rosbag_tools/compute_duration/README.md
rosbag_tools/compute_duration/__init__.py
rosbag_tools/compute_duration/__main__.py
rosbag_tools/compute_duration/duration_calculator.py
rosbag_tools/compute_duration/main.py
rosbag_tools/export_odom/README.md
rosbag_tools/export_odom/__init__.py
rosbag_tools/export_odom/__main__.py
rosbag_tools/export_odom/main.py
rosbag_tools/export_odom/odometry_exporter.py
rosbag_tools/split/README.md
rosbag_tools/split/__init__.py
rosbag_tools/split/__main__.py
rosbag_tools/split/main.py
rosbag_tools/split/splitter.py
rosbag_tools/topic_compare/README.md
rosbag_tools/topic_compare/__init__.py
rosbag_tools/topic_compare/__main__.py
rosbag_tools/topic_compare/main.py
rosbag_tools/topic_compare/topic_comparator.py
rosbag_tools/topic_remove/README.md
rosbag_tools/topic_remove/__init__.py
rosbag_tools/topic_remove/__main__.py
rosbag_tools/topic_remove/main.py
rosbag_tools/topic_remove/topic_remover.py
rosbag_tools-0.0.10.dist-info/entry_points.txt
rosbag_tools-0.0.10.dist-info/LICENSE
rosbag_tools-0.0.10.dist-info/WHEEL
rosbag_tools-0.0.10.dist-info/METADATA
rosbag_tools-0.0.10.dist-info/RECORD
