Metadata-Version: 2.1
Name: rosbag-tools
Version: 0.0.10
Summary: A ROS-agnostic toolbox for common rosbag operations
Author-email: damienlarocque <phicoltan@gmail.com>
Requires-Python: >=3.8
Classifier: License :: OSI Approved :: GNU General Public License v3 or later (GPLv3+)
Classifier: Development Status :: 5 - Production/Stable
Classifier: Intended Audience :: Science/Research
Classifier: Operating System :: OS Independent
Classifier: Programming Language :: Python
Classifier: Programming Language :: Python :: 3
Classifier: Programming Language :: Python :: 3.9
Classifier: Programming Language :: Python :: 3.10
Classifier: Programming Language :: Python :: 3.11
Requires-Dist: click
Requires-Dist: pandas
Requires-Dist: pyyaml
Requires-Dist: rosbags==0.9.16
Requires-Dist: tqdm
Requires-Dist: black ; extra == "dev"
Requires-Dist: pylint ; extra == "dev"
Requires-Dist: bump2version ; extra == "dev"
Requires-Dist: matplotlib ; extra == "plot"
Project-URL: Homepage, https://github.com/IamPhytan/rosbag-tools
Project-URL: Repository on GitHub, https://github.com/IamPhytan/rosbag-tools
Project-URL: Repository on GitLab, https://gitlab.com/damienlarocque/rosbag-tools
Provides-Extra: dev
Provides-Extra: plot
